cvxopt/gsl.cpython-313-x86_64-linux-gnu.so
cvxopt/lapack.cpython-313-x86_64-linux-gnu.so
cvxopt/blas.cpython-313-x86_64-linux-gnu.so
cvxopt/misc_solvers.cpython-313-x86_64-linux-gnu.so
cvxopt/info.py
cvxopt/__init__.py
cvxopt/base.cpython-313-x86_64-linux-gnu.so
cvxopt/glpk.cpython-313-x86_64-linux-gnu.so
cvxopt/cholmod.cpython-313-x86_64-linux-gnu.so
cvxopt/_version.py
cvxopt/fftw.cpython-313-x86_64-linux-gnu.so
cvxopt/msk.py
cvxopt/misc.py
cvxopt/coneprog.py
cvxopt/umfpack.cpython-313-x86_64-linux-gnu.so
cvxopt/amd.cpython-313-x86_64-linux-gnu.so
cvxopt/dsdp.cpython-313-x86_64-linux-gnu.so
cvxopt/modeling.py
cvxopt/cvxprog.py
cvxopt/solvers.py
cvxopt/printing.py
cvxopt-1.3.2.dist-info/METADATA
cvxopt-1.3.2.dist-info/WHEEL
cvxopt-1.3.2.dist-info/LICENSE
cvxopt-1.3.2.dist-info/RECORD
cvxopt-1.3.2.dist-info/top_level.txt
cvxopt.libs/libcamd-28bb7d13.so.2.4.1
cvxopt.libs/libquadmath-776d53b6.so.0.0.0
cvxopt.libs/libglpk-49b4dd37.so.40.3.0
cvxopt.libs/libopenblas-r0-11edc3fa.3.15.so
cvxopt.libs/libamd-a26d1aab.so.2.4.1
cvxopt.libs/libgmp-d944b113.so.10.3.2
cvxopt.libs/libfftw3-6b983104.so.3.5.5
cvxopt.libs/libgfortran-93980b03.so.5.0.0
cvxopt.libs/libcolamd-dc193ab4.so.2.9.1
cvxopt.libs/libgsl-b64c76bc.so.23.1.0
cvxopt.libs/libumfpack-2e055419.so.5.7.1
cvxopt.libs/libdsdp-5924495b.so
cvxopt.libs/libsatlas-6c1f674f.so.3.10
cvxopt.libs/libccolamd-b4f1d742.so.2.9.1
cvxopt.libs/libcholmod-8f6cf142.so.3.0.6
cvxopt.libs/libsuitesparseconfig-e4e8c4aa.so.4.4.4
